odoo/addons/account_promissory_note_caixabank/README.rst
odoo/addons/account_promissory_note_caixabank/__init__.py
odoo/addons/account_promissory_note_caixabank/__manifest__.py
odoo/addons/account_promissory_note_caixabank/data/account_promissory_note_report_data.xml
odoo/addons/account_promissory_note_caixabank/i18n/account_promissory_note_caixabank.pot
odoo/addons/account_promissory_note_caixabank/i18n/es.po
odoo/addons/account_promissory_note_caixabank/readme/CONFIGURE.rst
odoo/addons/account_promissory_note_caixabank/readme/CONTRIBUTORS.rst
odoo/addons/account_promissory_note_caixabank/readme/DESCRIPTION.rst
odoo/addons/account_promissory_note_caixabank/readme/USAGE.rst
odoo/addons/account_promissory_note_caixabank/report/__init__.py
odoo/addons/account_promissory_note_caixabank/report/account_promissory_note_writing_report.xml
odoo/addons/account_promissory_note_caixabank/report/check_print.py
odoo/addons/account_promissory_note_caixabank/static/description/icon.png
odoo/addons/account_promissory_note_caixabank/static/description/index.html
odoo/addons/account_promissory_note_caixabank/views/report_promissory_note.xml
odoo13_addon_account_promissory_note_caixabank-13.0.1.0.1.dist-info/METADATA
odoo13_addon_account_promissory_note_caixabank-13.0.1.0.1.dist-info/WHEEL
odoo13_addon_account_promissory_note_caixabank-13.0.1.0.1.dist-info/top_level.txt
odoo13_addon_account_promissory_note_caixabank-13.0.1.0.1.dist-info/RECORD
