Metadata-Version: 2.1
Name: odoo13-addon-account-promissory-note-caixabank
Version: 13.0.1.0.1
Summary: Impresión de pagaré CaixaBank A4
Home-page: https://github.com/OCA/l10n-spain
Author: Tecnativa, Odoo Community Association (OCA)
Author-email: support@odoo-community.org
License: AGPL-3
Platform: UNKNOWN
Classifier: Programming Language :: Python
Classifier: Framework :: Odoo
Classifier: License :: OSI Approved :: GNU Affero General Public License v3
Requires-Python: >=3.5
Requires-Dist: odoo13-addon-account-check-printing-report-base
Requires-Dist: odoo13-addon-account-payment-promissory-note
Requires-Dist: odoo (<13.1dev,>=13.0a)
